{
    "location": "havok/router/baseUrl",
    "type": "object",
    "methods": [
        {
            "name": "load",
            "scope": "normal",
            "types": [
                "function"
            ],
            "from": "havok/router/baseUrl",
            "parameters": [
                {
                    "name": "id",
                    "types": [
                        "undefined"
                    ],
                    "usage": "required"
                },
                {
                    "name": "require",
                    "types": [
                        "undefined"
                    ],
                    "usage": "required"
                },
                {
                    "name": "callback",
                    "types": [
                        "undefined"
                    ],
                    "usage": "required"
                }
            ],
            "returnTypes": []
        }
    ],
    "rootPath": "../../../",
    "shortName": "baseUrl"
}